embedtools/__init__.py
embedtools-0.2.0.dist-info/LICENSE
embedtools-0.2.0.dist-info/METADATA
embedtools-0.2.0.dist-info/WHEEL
embedtools-0.2.0.dist-info/top_level.txt
embedtools-0.2.0.dist-info/RECORD
