Metadata-Version: 2.1
Name: embedtools
Version: 0.2.0
Summary: Embed tools package for discord.py embeds.
Home-page: https://github.com/ItsKas/embedcolors
Author: Lukas Canter
Author-email: lilcanter07@gmail.com
License: UNKNOWN
Platform: UNKNOWN
Classifier: Programming Language :: Python :: 3
Classifier: License :: OSI Approved :: MIT License
Classifier: Operating System :: OS Independent
Requires-Python: >=3.6
